autofish/__init__.py
autofish/__main__.py
autofish/autofish_gui.py
autofish/automator.py
autofish/coordinator.py
autofish/imager.py
autofish-0.0.8.dist-info/METADATA
autofish-0.0.8.dist-info/WHEEL
autofish-0.0.8.dist-info/entry_points.txt
autofish-0.0.8.dist-info/top_level.txt
autofish-0.0.8.dist-info/zip-safe
autofish-0.0.8.dist-info/RECORD
