Metadata-Version: 2.4
Name: autofish
Version: 0.0.8
Summary: Control of automated fluidics system
Home-page: https://github.com/fish-quant/autofish
Author: Florian Mueller
Author-email: fmueller@pasteur.fr
Classifier: Programming Language :: Python :: 3
Classifier: License :: OSI Approved :: MIT License
Classifier: Operating System :: Microsoft :: Windows :: Windows 10
Requires-Python: >=3.10
Requires-Dist: pyserial
Requires-Dist: FreeSimpleGUI==5.2.0
Requires-Dist: pyyaml
Requires-Dist: numpy
Provides-Extra: pycromanager
Requires-Dist: pycromanager; extra == "pycromanager"
